{
    "2020bb": "2020 Super Baseball (set 1)",
    "2020bba": "2020 Super Baseball (set 2)",
    "2020bbh": "2020 Super Baseball (set 3)",
    "20pacgal": "Ms. Pac-Man/Galaga - 20th Anniversary Class of 1981 Reunion (V1.08)",
    "20pacgalr0": "Ms. Pac-Man/Galaga - 20th Anniversary Class of 1981 Reunion (V1.00)",
    "20pacgalr1": "Ms. Pac-Man/Galaga - 20th Anniversary Class of 1981 Reunion (V1.01)",
    "20pacgalr2": "Ms. Pac-Man/Galaga - 20th Anniversary Class of 1981 Reunion (V1.02)",
    "20pacgalr3": "Ms. Pac-Man/Galaga - 20th Anniversary Class of 1981 Reunion (V1.03)",
    "20pacgalr4": "Ms. Pac-Man/Galaga - 20th Anniversary Class of 1981 Reunion (V1.04)",
    "240in1ar": "Mini Arcade Machine (Thumbs Up, 240IN1ARC)",
    "24_130": "24 v1.30",
    "24_140": "24 v1.40",
    "24_144": "24 v1.44",
    "24_150": "24 v1.50",
    "24cdjuke": "Midcoin Juke Box 24CD",
    "25pacman": "Pac-Man - 25th Anniversary Edition (Rev 3.00)",
    "25pacmano": "Pac-Man - 25th Anniversary Edition (Rev 2.00)",
    "280zzzap": "280-ZZZAP",
    "2mindril": "Two Minute Drill (Ver 2.93A 1994/02/16)",
    "2spicy": "2 Spicy",
    "2joysnd": "PET Dual Joysticks and Sound",
    "21064": "DEC Alpha 21064",
    "22vp932": "Philips 22VP932",
    "22vp931": "Philips 22VP931",
    "2804": "Parallel EEPROM 2804 (512x8)",
    "2816": "Parallel EEPROM 2816 (2048x8)",
    "2864": "Parallel EEPROM 2864 (8192x8)",
    "28256": "Parallel EEPROM 28256 (32768x8)",
    "28512": "Parallel EEPROM 28512 (65536x8)",
    "28010": "Parallel EEPROM 28010 (131072x8)",
    "28020": "Parallel EEPROM 28020 (262144x8)",
    "28040": "Parallel EEPROM 28040 (524288x8)",
    "24c01": "24C01 I2C Memory",
    "24c02": "24C02 I2C Memory",
    "24c04": "24C04 I2C Memory",
    "24c08": "24C08 I2C Memory",
    "24c16": "24C16 I2C Memory",
    "24c64": "24C64 I2C Memory",
    "24c512": "24C512 I2C Memory"
}